foxglovetree/__init__.py
foxglovetree-0.1.dist-info/LICENSE.txt
foxglovetree-0.1.dist-info/METADATA
foxglovetree-0.1.dist-info/WHEEL
foxglovetree-0.1.dist-info/top_level.txt
foxglovetree-0.1.dist-info/RECORD
