Metadata-Version: 2.1
Name: foxglovetree
Version: 0.1
Summary: The foxglovetree module
Home-page: https://aihospital.ncchd.go.jp/foxglovetree
Author: Kohji
Author-email: okamura-k@ncchd.go.jp
License: MIT License
Keywords: NCCHD
License-File: LICENSE.txt
